setup.py
canoe/__init__.py
canoe/canoe.py
canoe/data.py
canoe/main.py
canoe/watch.py
canoe.egg-info/PKG-INFO
canoe.egg-info/SOURCES.txt
canoe.egg-info/dependency_links.txt
canoe.egg-info/entry_points.txt
canoe.egg-info/requires.txt
canoe.egg-info/top_level.txt
canoe/config/__init__.py
canoe/config/ast.py
canoe/config/config.py
canoe/config/lex.py
canoe/config/parser.py
canoe/config/test.py
canoe/filters/__init__.py
canoe/filters/simple.py
canoe/routes/__init__.py
canoe/routes/simple.py