Metadata-Version: 1.0
Name: canoe
Version: 0.1.1
Summary: Carve out log files and paddle
Home-page: https://github.com/apgwoz/canoe
Author: Andrew Gwozdziewycz
Author-email: web@apgwoz.com
License: GPL
Keywords: log analyze alert monitor
Platform: UNKNOWN
